espider/__init__.py
espider/queues.py
espider/request.py
espider/response.py
espider/selector.py
espider/spider.py
espider/test.py
espider/utils.py
espider/_utils/__init__.py
espider/_utils/_bs4.py
espider/_utils/_colorlog.py
espider/_utils/_requests.py
espider-1.7.3.dist-info/LICENSE
espider-1.7.3.dist-info/METADATA
espider-1.7.3.dist-info/WHEEL
espider-1.7.3.dist-info/top_level.txt
espider-1.7.3.dist-info/RECORD
