Metadata-Version: 2.1
Name: espider
Version: 1.7.3
Summary: easy spider
Home-page: https://github.com/gitduk/espider
Author: kaige
Author-email: wdkany@gmail.com
License: MIT
Platform: UNKNOWN
Classifier: License :: OSI Approved :: MIT License
Classifier: Programming Language :: Python
Classifier: Programming Language :: Python :: 3
Classifier: Programming Language :: Python :: 3.6
Classifier: Programming Language :: Python :: Implementation :: CPython
Classifier: Programming Language :: Python :: Implementation :: PyPy
Requires-Python: >=3.6.0
Requires-Dist: aiohttp
Requires-Dist: lxml
Requires-Dist: parsel
Requires-Dist: pymysql
Requires-Dist: redis
Requires-Dist: requests
Requires-Dist: six
Requires-Dist: w3lib
